fitsearchcv/__init__.py
fitsearchcv/selectors.py
fitsearchcv-1.0.3.dist-info/licenses/LICENSE
fitsearchcv-1.0.3.dist-info/METADATA
fitsearchcv-1.0.3.dist-info/WHEEL
fitsearchcv-1.0.3.dist-info/top_level.txt
fitsearchcv-1.0.3.dist-info/RECORD
